<?xml version="1.0" encoding="utf-8" ?>
<dwsync>
<file name="hero.php" server="ftp.lojasmarim.com" local="134203421707860224" remote="134203349400000000" Dst="0" />
<file name="benefits_cards.php" server="ftp.lojasmarim.com" local="134203441604544815" remote="134203369200000000" Dst="0" />
<file name="text.php" server="ftp.lojasmarim.com" local="134204675145394561" remote="134204602800000000" Dst="0" />
<file name="catalog_products.php" server="ftp.lojasmarim.com" local="134204679162349271" remote="134204607000000000" Dst="0" />
<file name="testimonials.php" server="ftp.lojasmarim.com" local="134204681997887492" remote="134204609400000000" Dst="0" />
<file name="cta_whatsapp.php" server="ftp.lojasmarim.com" local="134204684990516618" remote="134204612400000000" Dst="0" />
<file name="cta_button.php" server="ftp.lojasmarim.com" local="134204690209667534" remote="134204617800000000" Dst="0" />
<file name="lead_form.php" server="ftp.lojasmarim.com" local="134204695295763663" remote="134204623200000000" Dst="0" />
<file name="blog_header.php" server="ftp.lojasmarim.com" local="134204749882307141" remote="134204677800000000" Dst="0" />
<file name="blog_content.php" server="ftp.lojasmarim.com" local="134204807023274631" remote="134204734800000000" Dst="0" />
<file name="blog_video.php" server="ftp.lojasmarim.com" local="134204777610288917" remote="134204705400000000" Dst="0" />
<file name="blog_list.php" server="ftp.lojasmarim.com" local="134204777615582759" remote="134204705400000000" Dst="0" />
<file name="blog_text.php" server="ftp.lojasmarim.com" local="134204777611826096" remote="134204705400000000" Dst="0" />
<file name="blog_image.php" server="ftp.lojasmarim.com" local="134204777617635535" remote="134204705400000000" Dst="0" />
<file name="blog_quote.php" server="ftp.lojasmarim.com" local="134204777613699099" remote="134204705400000000" Dst="0" />
<file name="blog_cta.php" server="ftp.lojasmarim.com" local="134204777619842671" remote="134204705400000000" Dst="0" />
</dwsync>